sphinxjp.shibukawa-0.1.6-py2.7-nspkg.pth
sphinxjp/shibukawa/__init__.py
sphinxjp/shibukawa/core.py
sphinxjp/shibukawa/parser.py
sphinxjp.shibukawa-0.1.6.dist-info/DESCRIPTION.rst
sphinxjp.shibukawa-0.1.6.dist-info/METADATA
sphinxjp.shibukawa-0.1.6.dist-info/metadata.json
sphinxjp.shibukawa-0.1.6.dist-info/namespace_packages.txt
sphinxjp.shibukawa-0.1.6.dist-info/RECORD
sphinxjp.shibukawa-0.1.6.dist-info/top_level.txt
sphinxjp.shibukawa-0.1.6.dist-info/WHEEL
