Metadata-Version: 2.0
Name: sphinxjp.shibukawa
Version: 0.1.6
Summary: Sphinx calendar extension
Home-page: http://bitbucket.org/tk0miya/
Author: Takeshi KOMIYA
Author-email: i.tkomiya@gmail.com
License: BSD
Download-URL: http://pypi.python.org/pypi/sphinxjp.shibukawa
Platform: any
Classifier: Development Status :: 4 - Beta
Classifier: Environment :: Console
Classifier: Environment :: Web Environment
Classifier: Intended Audience :: Developers
Classifier: License :: OSI Approved :: BSD License
Classifier: Operating System :: OS Independent
Classifier: Programming Language :: Python
Classifier: Topic :: Documentation
Classifier: Topic :: Utilities
Requires-Dist: Sphinx (>=0.6)
Requires-Dist: funcparserlib
